{
    "stamps": {
        "MTV": {
            "id": "MTV",
            "secondaryIdentifier": "1",
            "name": "Blue Ridge Regional Airport",
            "coordinates": {
                "latitude": 36.6307525,
                "longitude": -80.0183383
            },
            "elevation": 940.9,
            "length": 5002,
            "type": "airport",
            "icon": "airplane",
            "notes": "",
            "alert": ""
        },
        "0VG": {
            "id": "0VG",
            "secondaryIdentifier": "1",
            "name": "Lee County Airport",
            "coordinates": {
                "latitude": 36.6540850,
                "longitude": -83.2178467
            },
            "elevation": 1410.9,
            "length": 5003,
            "type": "airport",
            "icon": "airplane",
            "notes": "",
            "alert": ""
        },
        "LNP": {
            "id": "LNP",
            "secondaryIdentifier": "1",
            "name": "Lonesome Pine Airport",
            "coordinates": {
                "latitude": 36.9875178,
                "longitude": -82.5299975
            },
            "elevation": 2684.3,
            "length": 5280,
            "type": "airport",
            "icon": "airplane",
            "notes": "",
            "alert": ""
        },
        "MKJ": {
            "id": "MKJ",
            "secondaryIdentifier": "1",
            "name": "Mountain Empire Airport",
            "coordinates": {
                "latitude": 36.8948489,
                "longitude": -81.3499461
            },
            "elevation": 2558.2,
            "length": 5252,
            "type": "airport",
            "icon": "airplane",
            "notes": "",
            "alert": ""
        },
        "PSK": {
            "id": "PSK",
            "secondaryIdentifier": "1",
            "name": "New River Valley Airport",
            "coordinates": {
                "latitude": 37.1373364,
                "longitude": -80.6784794
            },
            "elevation": 2104.5,
            "length": 6201,
            "type": "airport",
            "icon": "airplane",
            "notes": "",
            "alert": ""
        },
        "JFZ": {
            "id": "JFZ",
            "secondaryIdentifier": "1",
            "name": "Tazewell County Airport",
            "coordinates": {
                "latitude": 37.0637464,
                "longitude": -81.7982658
            },
            "elevation": 2653.1,
            "length": 4299,
            "type": "airport",
            "icon": "airplane",
            "notes": "",
            "alert": ""
        },
        "HLX": {
            "id": "HLX",
            "secondaryIdentifier": "1",
            "name": "Twin County Airport",
            "coordinates": {
                "latitude": 36.7661108,
                "longitude": -80.8235600
            },
            "elevation": 2693.6,
            "length": 4299,
            "type": "airport",
            "icon": "airplane",
            "notes": "",
            "alert": ""
        },
        "VJI": {
            "id": "VJI",
            "secondaryIdentifier": "1",
            "name": "Virginia Highlands Airport",
            "coordinates": {
                "latitude": 36.6871025,
                "longitude": -82.0333267
            },
            "elevation": 2087.4,
            "length": 4471,
            "type": "airport",
            "icon": "airplane",
            "notes": "",
            "alert": ""
        },
        "BCB": {
            "id": "BCB",
            "secondaryIdentifier": "1",
            "name": "Virginia Tech/Montgomery Executive Airport",
            "coordinates": {
                "latitude": 37.2093867,
                "longitude": -80.4120900
            },
            "elevation": 2119.5,
            "length": 5501,
            "type": "airport",
            "icon": "airplane",
            "notes": "",
            "alert": ""
        },
        "VBW": {
            "id": "VBW",
            "secondaryIdentifier": "2",
            "name": "Bridgewater Air Park",
            "coordinates": {
                "latitude": 38.3667375,
                "longitude": -78.9603342
            },
            "elevation": 1165,
            "length": 2745,
            "type": "airport",
            "icon": "airplane",
            "notes": "",
            "alert": ""
        },
        "CHO": {
            "id": "CHO",
            "secondaryIdentifier": "2",
            "name": "Charlottesville-Albemarle Airport",
            "coordinates": {
                "latitude": 38.1396428,
                "longitude": -78.4523442
            },
            "elevation": 640.1,
            "length": 6801,
            "type": "airport",
            "icon": "airplane",
            "notes": "",
            "alert": ""
        },
        "W13": {
            "id": "W13",
            "secondaryIdentifier": "2",
            "name": "Eagles Nest Airport",
            "coordinates": {
                "latitude": 38.0769375,
                "longitude": -78.9444375
            },
            "elevation": 1436,
            "length": 2004,
            "type": "airport",
            "icon": "airplane",
            "notes": "",
            "alert": ""
        },
        "FRR": {
            "id": "FRR",
            "secondaryIdentifier": "2",
            "name": "Front Royal-Warren County Airport",
            "coordinates": {
                "latitude": 38.9175122,
                "longitude": -78.2533733
            },
            "elevation": 703.6,
            "length": 3008,
            "type": "airport",
            "icon": "airplane",
            "notes": "",
            "alert": ""
        },
        "GVE": {
            "id": "GVE",
            "secondaryIdentifier": "2",
            "name": "Gordonsville Municipal Airport",
            "coordinates": {
                "latitude": 38.1559961,
                "longitude": -78.1657800
            },
            "elevation": 454,
            "length": 2300,
            "type": "airport",
            "icon": "airplane",
            "notes": "",
            "alert": ""
        },
        "HSP": {
            "id": "HSP",
            "secondaryIdentifier": "2",
            "name": "Ingalls Field Airport",
            "coordinates": {
                "latitude": 37.9514444,
                "longitude": -79.8338944
            },
            "elevation": 3792.7,
            "length": 5600,
            "type": "airport",
            "icon": "airplane",
            "notes": "",
            "alert": ""
        },
        "LUA": {
            "id": "LUA",
            "secondaryIdentifier": "2",
            "name": "Luray Caverns Airport",
            "coordinates": {
                "latitude": 38.6667105,
                "longitude": -78.5008350
            },
            "elevation": 902.4,
            "length": 3126,
            "type": "airport",
            "icon": "airplane",
            "notes": "",
            "alert": ""
        },
        "8W2": {
            "id": "8W2",
            "secondaryIdentifier": "2",
            "name": "New Market Airport",
            "coordinates": {
                "latitude": 38.6559847,
                "longitude": -78.7084958
            },
            "elevation": 962.7,
            "length": 2920,
            "type": "airport",
            "icon": "airplane",
            "notes": "",
            "alert": ""
        },
        "OMH": {
            "id": "OMH",
            "secondaryIdentifier": "2",
            "name": "Orange County Airport",
            "coordinates": {
                "latitude": 38.2472028,
                "longitude": -78.0456211
            },
            "elevation": 464.4,
            "length": 3200,
            "type": "airport",
            "icon": "airplane",
            "notes": "",
            "alert": ""
        },
        "ROA": {
            "id": "ROA",
            "secondaryIdentifier": "2",
            "name": "Roanoke-Blacksburg Regional Airport",
            "coordinates": {
                "latitude": 37.3254722,
                "longitude": -79.9754167
            },
            "elevation": 1175.2,
            "length": 6800,
            "type": "airport",
            "icon": "airplane",
            "notes": "",
            "alert": ""
        },
        "SHD": {
            "id": "SHD",
            "secondaryIdentifier": "2",
            "name": "Shenandoah Valley Regional Airport",
            "coordinates": {
                "latitude": 38.2638333,
                "longitude": -78.8964444
            },
            "elevation": 1201,
            "length": 6002,
            "type": "airport",
            "icon": "airplane",
            "notes": "",
            "alert": ""
        },
        "CJR": {
            "id": "CJR",
            "secondaryIdentifier": "3",
            "name": "Culpeper Regional Airport",
            "coordinates": {
                "latitude": 38.5254722,
                "longitude": -77.8596389
            },
            "elevation": 315.5,
            "length": 5000,
            "type": "airport",
            "icon": "airplane",
            "notes": "",
            "alert": ""
        },
        "JYO": {
            "id": "JYO",
            "secondaryIdentifier": "3",
            "name": "Leesburg Executive Airport",
            "coordinates": {
                "latitude": 39.077965,
                "longitude": -77.557500
            },
            "elevation": 389.5,
            "length": 5500,
            "type": "airport",
            "icon": "airplane",
            "notes": "",
            "alert": ""
        },
        "HEF": {
            "id": "HEF",
            "secondaryIdentifier": "3",
            "name": "Manassas Regional Airport",
            "coordinates": {
                "latitude": 38.7210247,
                "longitude": -77.5151047
            },
            "elevation": 192.2,
            "length": 6200,
            "type": "airport",
            "icon": "airplane",
            "notes": "",
            "alert": ""
        },
        "EZF": {
            "id": "EZF",
            "secondaryIdentifier": "3",
            "name": "Shannon Airport",
            "coordinates": {
                "latitude": 38.2668953,
                "longitude": -77.4492403
            },
            "elevation": 85,
            "length": 2902,
            "type": "airport",
            "icon": "airplane",
            "notes": "",
            "alert": ""
        },
        "RMN": {
            "id": "RMN",
            "secondaryIdentifier": "3",
            "name": "Stafford Regional Airport",
            "coordinates": {
                "latitude": 38.3981111,
                "longitude": -77.4554722
            },
            "elevation": 211.2,
            "length": 5000,
            "type": "airport",
            "icon": "airplane",
            "notes": "",
            "alert": ""
        },
        "HWY": {
            "id": "HWY",
            "secondaryIdentifier": "3",
            "name": "Warrenton-Fauquier Airport",
            "coordinates": {
                "latitude": 38.5862853,
                "longitude": -77.7106308
            },
            "elevation": 336.2,
            "length": 5000,
            "type": "airport",
            "icon": "airplane",
            "notes": "",
            "alert": ""
        },
        "IAD": {
            "id": "IAD",
            "secondaryIdentifier": "3",
            "name": "Washington Dulles International Airport",
            "coordinates": {
                "latitude": 38.9474564,
                "longitude": -77.4599286
            },
            "elevation": 312.3,
            "length": 11500,
            "type": "airport",
            "icon": "airplane",
            "notes": "",
            "alert": ""
        },
        "DCA": {
            "id": "DCA",
            "secondaryIdentifier": "3",
            "name": "Ronald Reagan Washington National Airport",
            "coordinates": {
                "latitude": 38.8514403,
                "longitude": -77.0377214
            },
            "elevation": 14.1,
            "length": 7169,
            "type": "airport",
            "icon": "airplane",
            "notes": "",
            "alert": ""
        },
        "OKV": {
            "id": "OKV",
            "secondaryIdentifier": "3",
            "name": "Winchester Regional Airport",
            "coordinates": {
                "latitude": 39.1435278,
                "longitude": -78.1444444
            },
            "elevation": 726.2,
            "length": 5498,
            "type": "airport",
            "icon": "airplane",
            "notes": "",
            "alert": ""
        },
        "FCI": {
            "id": "FCI",
            "secondaryIdentifier": "4",
            "name": "Chesterfield County Airport",
            "coordinates": {
                "latitude": 37.4064444,
                "longitude": -77.5248333
            },
            "elevation": 236.1,
            "length": 5500,
            "type": "airport",
            "icon": "airplane",
            "notes": "",
            "alert": ""
        },
        "OFP": {
            "id": "OFP",
            "secondaryIdentifier": "4",
            "name": "Hanover County Municipal Airport",
            "coordinates": {
                "latitude": 37.7089444,
                "longitude": -77.4366389
            },
            "elevation": 206.5,
            "length": 5402,
            "type": "airport",
            "icon": "airplane",
            "notes": "",
            "alert": ""
        },
        "7W4": {
            "id": "7W4",
            "secondaryIdentifier": "4",
            "name": "Lake Anna Airport",
            "coordinates": {
                "latitude": 38.0938,
                "longitude": -77.7904
            },
            "elevation": 351.2,
            "length": 5498,
            "type": "airport",
            "icon": "airplane",
            "notes": "",
            "alert": ""
        },
        "LKU": {
            "id": "LKU",
            "secondaryIdentifier": "4",
            "name": "Louisa County",
            "coordinates": {
                "latitude": 37.9658194,
                "longitude": -77.7459028
            },
            "elevation": 726.2,
            "length": 2558,
            "type": "airport",
            "icon": "airplane",
            "notes": "",
            "alert": ""
        },
        "W96": {
            "id": "W96",
            "secondaryIdentifier": "4",
            "name": "New Kent County Airport",
            "coordinates": {
                "latitude": 37.5034294,
                "longitude": -77.1265583
            },
            "elevation": 120.7,
            "length": 3602,
            "type": "airport",
            "icon": "airplane",
            "notes": "",
            "alert": ""
        },
        "RIC": {
            "id": "RIC",
            "secondaryIdentifier": "4",
            "name": "Richmond International Airport",
            "coordinates": {
                "latitude": 37.5051811,
                "longitude": -77.3197386
            },
            "elevation": 167.5,
            "length": 9003,
            "type": "airport",
            "icon": "airplane",
            "notes": "",
            "alert": ""
        },
        "XSA": {
            "id": "XSA",
            "secondaryIdentifier": "4",
            "name": "Tappahannock-Essex County Airport",
            "coordinates": {
                "latitude": 37.8596092,
                "longitude": -76.8941194
            },
            "elevation": 135.2,
            "length": 4300,
            "type": "airport",
            "icon": "airplane",
            "notes": "",
            "alert": ""
        },
        "BKT": {
            "id": "BKT",
            "secondaryIdentifier": "5",
            "name": "Allen C. Perkinson Municipal Airport",
            "coordinates": {
                "latitude": 37.0747673,
                "longitude": -77.9565984
            },
            "elevation": 437.4,
            "length": 5333,
            "type": "airport",
            "icon": "airplane",
            "notes": "",
            "alert": ""
        },
        "0V4": {
            "id": "0V4",
            "secondaryIdentifier": "5",
            "name": "Brookneal-Campbell County Airport",
            "coordinates": {
                "latitude": 37.1417222,
                "longitude": -79.0163889
            },
            "elevation": 596.6,
            "length": 3798,
            "type": "airport",
            "icon": "airplane",
            "notes": "",
            "alert": ""
        },
        "W81": {
            "id": "W81",
            "secondaryIdentifier": "5",
            "name": "Crewe Municipal Airport",
            "coordinates": {
                "latitude": 37.1810122,
                "longitude": -78.0984747
            },
            "elevation": 422,
            "length": 3300,
            "type": "airport",
            "icon": "airplane",
            "notes": "",
            "alert": ""
        },
        "DAN": {
            "id": "DAN",
            "secondaryIdentifier": "5",
            "name": "Danville Regional Airport",
            "coordinates": {
                "latitude": 36.5724722,
                "longitude": -79.3362500
            },
            "elevation": 571.1,
            "length": 5900,
            "type": "airport",
            "icon": "airplane",
            "notes": "",
            "alert": ""
        },
        "PTB": {
            "id": "PTB",
            "secondaryIdentifier": "5",
            "name": "Dinwiddie County Airport",
            "coordinates": {
                "latitude": 37.1843014,
                "longitude": -77.5061744
            },
            "elevation": 192.7,
            "length": 5002,
            "type": "airport",
            "icon": "airplane",
            "notes": "",
            "alert": ""
        },
        "W24": {
            "id": "W24",
            "secondaryIdentifier": "5",
            "name": "Falwell Airport",
            "coordinates": {
                "latitude": 37.3779208,
                "longitude": -79.1222453
            },
            "elevation": 939,
            "length": 2932,
            "type": "airport",
            "icon": "airplane",
            "notes": "",
            "alert": ""
        },
        "FVX": {
            "id": "FVX",
            "secondaryIdentifier": "5",
            "name": "Farmville Regional Airport",
            "coordinates": {
                "latitude": 37.3575278,
                "longitude": -78.4378056
            },
            "elevation": 415.7,
            "length": 4400,
            "type": "airport",
            "icon": "airplane",
            "notes": "",
            "alert": ""
        },
        "LYH": {
            "id": "LYH",
            "secondaryIdentifier": "5",
            "name": "Lynchburg Regional Airport",
            "coordinates": {
                "latitude": 37.3253889,
                "longitude": -79.2012222
            },
            "elevation": 938.2,
            "length": 7100,
            "type": "airport",
            "icon": "airplane",
            "notes": "",
            "alert": ""
        },
        "W90": {
            "id": "W90",
            "secondaryIdentifier": "5",
            "name": "New London Airport",
            "coordinates": {
                "latitude": 37.2717278,
                "longitude": -79.3359000
            },
            "elevation": 842,
            "length": 3164,
            "type": "airport",
            "icon": "airplane",
            "notes": "",
            "alert": ""
        },
        "W91": {
            "id": "W91",
            "secondaryIdentifier": "5",
            "name": "Smith Mountain Lake Airport",
            "coordinates": {
                "latitude": 37.1077222,
                "longitude": -79.5924722
            },
            "elevation": 892.2,
            "length": 3058,
            "type": "airport",
            "icon": "airplane",
            "notes": "",
            "alert": ""
        },
        "W78": {
            "id": "W78",
            "secondaryIdentifier": "5",
            "name": "William M. Tuck Airport",
            "coordinates": {
                "latitude": 36.7093724,
                "longitude": -78.8483375
            },
            "elevation": 419.8,
            "length": 2065,
            "type": "airport",
            "icon": "airplane",
            "notes": "",
            "alert": ""
        },
        "CXE": {
            "id": "CXE",
            "secondaryIdentifier": "6",
            "name": "Chase City Municipal Airport",
            "coordinates": {
                "latitude": 36.7883356,
                "longitude": -78.5015536
            },
            "elevation": 503,
            "length": 3400,
            "type": "airport",
            "icon": "airplane",
            "notes": "",
            "alert": ""
        },
        "EMV": {
            "id": "EMV",
            "secondaryIdentifier": "6",
            "name": "Emporia-Greenville Regional Airport",
            "coordinates": {
                "latitude": 36.6868581,
                "longitude": -77.4827489
            },
            "elevation": 126.7,
            "length": 5010,
            "type": "airport",
            "icon": "airplane",
            "notes": "",
            "alert": ""
        },
        "FKN": {
            "id": "FKN",
            "secondaryIdentifier": "6",
            "name": "Franklin Municipal Airport",
            "coordinates": {
                "latitude": 36.7002964,
                "longitude": -76.9021356
            },
            "elevation": 40.3,
            "length": 4977,
            "type": "airport",
            "icon": "airplane",
            "notes": "",
            "alert": ""
        },
        "W63": {
            "id": "W63",
            "secondaryIdentifier": "6",
            "name": "Lake Country Regional Airport",
            "coordinates": {
                "latitude": 36.5963667,
                "longitude": -78.5597294
            },
            "elevation": 420.9,
            "length": 4007,
            "type": "airport",
            "icon": "airplane",
            "notes": "",
            "alert": ""
        },
        "LVL": {
            "id": "LVL",
            "secondaryIdentifier": "6",
            "name": "Lawrenceville-Brunswick Municipal Airport",
            "coordinates": {
                "latitude": 36.7746292,
                "longitude": -77.7937819
            },
            "elevation": 328.7,
            "length": 3020,
            "type": "airport",
            "icon": "airplane",
            "notes": "",
            "alert": ""
        },
        "W31": {
            "id": "W31",
            "secondaryIdentifier": "6",
            "name": "Lunenburg County Airport",
            "coordinates": {
                "latitude": 36.9604028,
                "longitude": -78.1851111
            },
            "elevation": 526,
            "length": 3000,
            "type": "airport",
            "icon": "airplane",
            "notes": "",
            "alert": ""
        },
        "AVC": {
            "id": "AVC",
            "secondaryIdentifier": "6",
            "name": "Mecklenburg-Brunswick Regional Airport",
            "coordinates": {
                "latitude": 36.6882778,
                "longitude": -78.0544722
            },
            "elevation": 441.4,
            "length": 5002,
            "type": "airport",
            "icon": "airplane",
            "notes": "",
            "alert": ""
        },
        "AKQ": {
            "id": "AKQ",
            "secondaryIdentifier": "6",
            "name": "Wakefield Municipal Airport",
            "coordinates": {
                "latitude": 36.9872222,
                "longitude": -77.0011389
            },
            "elevation": 111.4,
            "length": 4337,
            "type": "airport",
            "icon": "airplane",
            "notes": "",
            "alert": ""
        },
        "MFV": {
            "id": "MFV",
            "secondaryIdentifier": "7",
            "name": "Accomack County Airport",
            "coordinates": {
                "latitude": 37.6468789,
                "longitude": -75.7610453
            },
            "elevation": 47.6,
            "length": 5000,
            "type": "airport",
            "icon": "airplane",
            "notes": "",
            "alert": ""
        },
        "CPK": {
            "id": "CPK",
            "secondaryIdentifier": "7",
            "name": "Chesapeake Regional Airport",
            "coordinates": {
                "latitude": 36.6656175,
                "longitude": -76.3206558
            },
            "elevation": 18.7,
            "length": 5500,
            "type": "airport",
            "icon": "airplane",
            "notes": "",
            "alert": ""
        },
        "PVG": {
            "id": "PVG",
            "secondaryIdentifier": "7",
            "name": "Hampton Roads Executive Airport",
            "coordinates": {
                "latitude": 36.7807648,
                "longitude": -76.4512804
            },
            "elevation": 28,
            "length": 5350,
            "type": "airport",
            "icon": "airplane",
            "notes": "",
            "alert": ""
        },
        "W75": {
            "id": "W75",
            "secondaryIdentifier": "7",
            "name": "Hummel Field Airport",
            "coordinates": {
                "latitude": 37.6022708,
                "longitude": -76.4467292
            },
            "elevation": 30,
            "length": 2167,
            "type": "airport",
            "icon": "airplane",
            "notes": "",
            "alert": ""
        },
        "FYJ": {
            "id": "FYJ",
            "secondaryIdentifier": "7",
            "name": "Middle Peninsula Regional Airport",
            "coordinates": {
                "latitude": 37.5213611,
                "longitude": -76.7627500
            },
            "elevation": 20.4,
            "length": 5000,
            "type": "airport",
            "icon": "airplane",
            "notes": "",
            "alert": ""
        },
        "PHF": {
            "id": "PHF",
            "secondaryIdentifier": "7",
            "name": "Newport News/Williamsburg International Airport",
            "coordinates": {
                "latitude": 37.1318889,
                "longitude": -76.4929722
            },
            "elevation": 42.2,
            "length": 8003,
            "type": "airport",
            "icon": "airplane",
            "notes": "",
            "alert": ""
        },
        "ORF": {
            "id": "ORF",
            "secondaryIdentifier": "7",
            "name": "Norfolk International Airport",
            "coordinates": {
                "latitude": 36.8946042,
                "longitude": -76.2012292
            },
            "elevation": 26.4,
            "length": 9001,
            "type": "airport",
            "icon": "airplane",
            "notes": "",
            "alert": ""
        },
        "SFQ": {
            "id": "SFQ",
            "secondaryIdentifier": "7",
            "name": "Suffolk Executive Airport",
            "coordinates": {
                "latitude": 36.6828884,
                "longitude": -76.5996232
            },
            "elevation": 70.1,
            "length": 5007,
            "type": "airport",
            "icon": "airplane",
            "notes": "",
            "alert": ""
        },
        "TGI": {
            "id": "TGI",
            "secondaryIdentifier": "7",
            "name": "Tangier Island Airport",
            "coordinates": {
                "latitude": 37.8258653,
                "longitude": -75.9976625
            },
            "elevation": 5.4,
            "length": 2426,
            "type": "airport",
            "icon": "airplane",
            "notes": "",
            "alert": ""
        },
        "JGG": {
            "id": "JGG",
            "secondaryIdentifier": "7",
            "name": "Williamsburg-Jamestown Airport",
            "coordinates": {
                "latitude": 37.2391747,
                "longitude": -76.7160961
            },
            "elevation": 49,
            "length": 3204,
            "type": "airport",
            "icon": "airplane",
            "notes": "",
            "alert": ""
        },
        "M01": {
            "id": "M01",
            "secondaryIdentifier": "M",
            "name": "Air Power Park",
            "coordinates": {
                "latitude": 37.043270,
                "longitude": -76.366348
            },
            "elevation": 0,
            "length": 0,
            "type": "museum",
            "icon": "building.columns",
            "notes": "",
            "alert": ""
        },
        "M02": {
            "id": "M02",
            "secondaryIdentifier": "M",
            "name": "Military Aviation Museum",
            "coordinates": {
                "latitude": 36.678989,
                "longitude": -76.029770
            },
            "elevation": 0,
            "length": 0,
            "type": "museum",
            "icon": "building.columns",
            "notes": "",
            "alert": ""
        },
        "M03": {
            "id": "M03",
            "secondaryIdentifier": "M",
            "name": "Steven F. Udvar-Hazy Center (NASM)",
            "coordinates": {
                "latitude": 38.911060,
                "longitude": -77.443990
            },
            "elevation": 0,
            "length": 0,
            "type": "museum",
            "icon": "building.columns",
            "notes": "",
            "alert": ""
        },
        "M04": {
            "id": "M04",
            "secondaryIdentifier": "M",
            "name": "National Museum of the Marine Corps",
            "coordinates": {
                "latitude": 38.559350,
                "longitude": -77.322940
            },
            "elevation": 0,
            "length": 0,
            "type": "museum",
            "icon": "building.columns",
            "notes": "",
            "alert": ""
        },
        "M05": {
            "id": "M05",
            "secondaryIdentifier": "M",
            "name": "Science Museum of Virginia",
            "coordinates": {
                "latitude": 37.560631,
                "longitude": -77.466202
            },
            "elevation": 0,
            "length": 0,
            "type": "museum",
            "icon": "building.columns",
            "notes": "",
            "alert": ""
        },
        "M06": {
            "id": "M06",
            "secondaryIdentifier": "M",
            "name": "Shannon Air Museum",
            "coordinates": {
                "latitude": 38.267700,
                "longitude": -77.449059
            },
            "elevation": 0,
            "length": 0,
            "type": "museum",
            "icon": "building.columns",
            "notes": "",
            "alert": ""
        },
        "M07": {
            "id": "M07",
            "secondaryIdentifier": "M",
            "name": "U.S. Army Transportation Museum",
            "coordinates": {
                "latitude": 37.171870,
                "longitude": -76.571450
            },
            "elevation": 0,
            "length": 0,
            "type": "museum",
            "icon": "building.columns",
            "notes": "",
            "alert": ""
        },
        "M08": {
            "id": "M08",
            "secondaryIdentifier": "M",
            "name": "Virginia Air and Space Center",
            "coordinates": {
                "latitude": 37.023979,
                "longitude": -76.344299
            },
            "elevation": 0,
            "length": 0,
            "type": "museum",
            "icon": "building.columns",
            "notes": "",
            "alert": ""
        },
        "M09": {
            "id": "M09",
            "secondaryIdentifier": "M",
            "name": "Virginia Museum of Transportation",
            "coordinates": {
                "latitude": 37.273159,
                "longitude": -79.946312
            },
            "elevation": 0,
            "length": 0,
            "type": "museum",
            "icon": "building.columns",
            "notes": "",
            "alert": ""
        },
        "S01": {
            "id": "S01",
            "secondaryIdentifier": "S",
            "name": "Teaching Human Performance and Communication (FAASTeam events)",
            "coordinates": {
                "latitude": 37.241140,
                "longitude": -76.716470
            },
            "elevation": 0,
            "length": 0,
            "type": "seminar",
            "icon": "book.closed",
            "notes": "This seminar is Forum 2 in a 5-Forum Series titled 'Teaching Human Factors for CFIs'.  In this Forum we will discuss teaching human performance and communication.",
            "alert": ""
        },
        "S02": {
            "id": "S02",
            "secondaryIdentifier": "S",
            "name": "Drone Safety Day - Be Aware When You Are In The Air! (FAASTeam events)",
            "coordinates": {
                "latitude": 36.777630,
                "longitude": -76.447760
            },
            "elevation": 0,
            "length": 0,
            "type": "seminar",
            "icon": "book.closed",
            "notes": "Whether you're flying with the birds in a plane/rotorcraft, or flying with your feet on the ground. Drone safety affects all aviation enthusiasts. Come join the Richmond FAASTeam Representative DronePros at the Hampton Roads Executive Airport and learn all about where and how to fly drones safely. This will be a fun filled, open-to-the-public event focusing on safe and responsible drone flying. Highlights include exciting drone demonstrations, opportunity to operate the Zephyr drone simulator and much more! Engage with FAA Safety Team Representative DronePro's in a friendly setting, and witness the thrilling potential of drones in a safe controlled environment. Please spread the word. It's perfect for enthusiasts, families, and anyone curious about drones. ",
            "alert": ""
        },
        "F01": {
            "id": "F01",
            "secondaryIdentifier": "LAL",
            "name": "Lakeland Linder International Airport",
            "coordinates": {
                "latitude": 27.9876389,
                "longitude": -82.0190000
            },
            "elevation": 141.8,
            "length": 8500,
            "type": "flyIn",
            "icon": "airplane.departure",
            "notes": "The Sun ‘n Fun Fly-In",
            "alert": ""
        },
        "F02": {
            "id": "F02",
            "secondaryIdentifier": "OSH",
            "name": "Wittman Regional Airport",
            "coordinates": {
                "latitude": 43.9843708,
                "longitude": -88.5570425
            },
            "elevation": 808.5,
            "length": 8002,
            "type": "flyIn",
            "icon": "airplane.departure",
            "notes": "EAA AirVenture Oshkosh",
            "alert": ""
        },
        "T01": {
            "id": "T01",
            "secondaryIdentifier": "T",
            "name": "Jared's House",
            "coordinates": {
                "latitude": 35.224140,
                "longitude": -80.808580
            },
            "elevation": 0,
            "length": 0,
            "type": "test",
            "icon": "hammer.fill",
            "notes": "Test notes.",
            "alert": "Test alert."
        },
        "T02": {
            "id": "T02",
            "secondaryIdentifier": "T",
            "name": "Delta Office (RIC)",
            "coordinates": {
                "latitude": 37.527470,
                "longitude": -77.613370
            },
            "elevation": 0,
            "length": 0,
            "type": "test",
            "icon": "hammer.fill",
            "notes": "Test notes.",
            "alert": "Test alert."
        },
        "T03": {
            "id": "T03",
            "secondaryIdentifier": "T",
            "name": "Delta Office (RAL)",
            "coordinates": {
                "latitude": 35.881093,
                "longitude": -78.783783
            },
            "elevation": 0,
            "length": 0,
            "type": "test",
            "icon": "hammer.fill",
            "notes": "Test notes.",
            "alert": "Test alert."
        },
        "T04": {
            "id": "T04",
            "secondaryIdentifier": "T",
            "name": "Delta Office (CLT)",
            "coordinates": {
                "latitude": 35.085240,
                "longitude": -80.848240
            },
            "elevation": 0,
            "length": 0,
            "type": "test",
            "icon": "hammer.fill",
            "notes": "Test notes.",
            "alert": "Test alert."
        }
    }
}
